wwwurf_project_generator/__init__.py
wwwurf_project_generator/cli.py
wwwurf_project_generator/project_manager.py
wwwurf_project_generator-0.1.0.dist-info/LICENSE
wwwurf_project_generator-0.1.0.dist-info/METADATA
wwwurf_project_generator-0.1.0.dist-info/WHEEL
wwwurf_project_generator-0.1.0.dist-info/entry_points.txt
wwwurf_project_generator-0.1.0.dist-info/RECORD
