Metadata-Version: 2.1
Name: wwwurf-project-generator
Version: 0.1.0
Summary: A tool for generating multi-package Python projects
Home-page: https://worldwidewurf.io
License: MIT
Keywords: project,generator,poetry,package
Author: WorldWideWurf
Author-email: worldwidewurf@gmail.com
Requires-Python: >=3.9,<4.0
Classifier: License :: OSI Approved :: MIT License
Classifier: Programming Language :: Python :: 3
Classifier: Programming Language :: Python :: 3.9
Classifier: Programming Language :: Python :: 3.10
Classifier: Programming Language :: Python :: 3.11
Classifier: Programming Language :: Python :: 3.12
Classifier: Programming Language :: Python :: 3.13
Requires-Dist: toml (>=0.10.2,<0.11.0)
Project-URL: Repository, https://github.com/worldwidewurf-io/wwwurf-project-generator
